DDDisasterRecovery.py-0.1.2.data/scripts/compare_datacenters.py
DDDisasterRecovery.py-0.1.2.data/scripts/dd_comparison
DDDisasterRecovery.py-0.1.2.data/scripts/dd_f5
DDDisasterRecovery.py-0.1.2.data/scripts/dd_nsx
DDDisasterRecovery.py-0.1.2.dist-info/DESCRIPTION.rst
DDDisasterRecovery.py-0.1.2.dist-info/METADATA
DDDisasterRecovery.py-0.1.2.dist-info/RECORD
DDDisasterRecovery.py-0.1.2.dist-info/WHEEL
DDDisasterRecovery.py-0.1.2.dist-info/metadata.json
DDDisasterRecovery.py-0.1.2.dist-info/top_level.txt
dimensiondata/__init__.py
dimensiondata/dr/__init__.py
dimensiondata/dr/constants.py
dimensiondata/dr/utils.py
nsx/__init__.py
nsx/base_client.py
nsx/client.py
