Metadata-Version: 2.0
Name: DDDisasterRecovery.py
Version: 0.1.2
Summary: Base description, say what your package does here
Home-page: https://www.dimensiondata.com/
Author: Jeff Dunham
Author-email: UNKNOWN
License: UNKNOWN
Platform: UNKNOWN
Requires-Dist: DDF5Client.py
Requires-Dist: apache-libcloud
Requires-Dist: click
Requires-Dist: future
Requires-Dist: requests
Requires-Dist: six
Requires-Dist: xmltodict
